[
  {
    "line": 2,
    "elements": [
      {
        "line": 7,
        "name": "",
        "description": "",
        "type": "background",
        "keyword": "Background",
        "steps": [
          {
            "result": {
              "duration": 3028000000,
              "status": "passed"
            },
            "line": 8,
            "name": "a user is on Motors homepage",
            "match": {
              "location": "co.uk.motors.stepDefinitions.SearchCarsForSaleStepDefinitions.a_user_is_on_Motors_homepage()"
            },
            "keyword": "Given "
          },
          {
            "result": {
              "duration": 232000000,
              "status": "passed"
            },
            "line": 9,
            "name": "user accepts all cookies",
            "match": {
              "location": "co.uk.motors.stepDefinitions.SearchCarsForSaleStepDefinitions.userAcceptsAllCookies()"
            },
            "keyword": "And "
          }
        ]
      },
      {
        "start_timestamp": "2020-04-23T04:32:46.872Z",
        "before": [
          {
            "result": {
              "duration": 7060000000,
              "status": "passed"
            },
            "match": {
              "location": "co.uk.motors.hooks.Hook.setUp()"
            }
          }
        ],
        "line": 20,
        "name": "Customer is directed to register when they want to sell a car",
        "description": "",
        "id": "register-or-sign-in-to-sell-a-car;customer-is-directed-to-register-when-they-want-to-sell-a-car;;2",
        "after": [
          {
            "result": {
              "duration": 768000000,
              "status": "passed"
            },
            "match": {
              "location": "co.uk.motors.hooks.Hook.tearDown()"
            }
          }
        ],
        "type": "scenario",
        "keyword": "Scenario Outline",
        "steps": [
          {
            "result": {
              "duration": 153000000,
              "status": "passed"
            },
            "line": 13,
            "name": "a user clicks on Sell",
            "match": {
              "location": "co.uk.motors.stepDefinitions.RegisterToSellACarANDResearchCarsSteps.aUserClicksOnSell()"
            },
            "keyword": "When "
          },
          {
            "result": {
              "duration": 249000000,
              "status": "passed"
            },
            "line": 14,
            "name": "user enters valid \"titi@mailinator.com\"",
            "match": {
              "arguments": [
                {
                  "val": "\"titi@mailinator.com\"",
                  "offset": 18
                }
              ],
              "location": "co.uk.motors.stepDefinitions.RegisterToSellACarANDResearchCarsSteps.userEntersValid(java.lang.String)"
            },
            "keyword": "And "
          },
          {
            "result": {
              "duration": 118000000,
              "status": "passed"
            },
            "line": 15,
            "name": "user clicks on the signUp button",
            "match": {
              "location": "co.uk.motors.stepDefinitions.RegisterToSellACarANDResearchCarsSteps.userClicksOnTheSignUpButton()"
            },
            "keyword": "And "
          },
          {
            "result": {
              "duration": 56000000,
              "status": "passed"
            },
            "line": 16,
            "name": "the sign in page is displayed",
            "match": {
              "location": "co.uk.motors.stepDefinitions.RegisterToSellACarANDResearchCarsSteps.theSignInPageIsDisplayed()"
            },
            "keyword": "Then "
          }
        ],
        "tags": [
          {
            "name": "@regression"
          }
        ]
      }
    ],
    "name": "Register or sign in to sell a car",
    "description": "  As a user\n  I want the ability to register\n  So I can sell my car",
    "id": "register-or-sign-in-to-sell-a-car",
    "keyword": "Feature",
    "uri": "file:src/test/java/co/uk/motors/features/RegisterOrSignInToSellACar.feature",
    "tags": []
  },
  {
    "line": 1,
    "elements": [
      {
        "line": 6,
        "name": "",
        "description": "",
        "type": "background",
        "keyword": "Background",
        "steps": [
          {
            "result": {
              "duration": 2845000000,
              "status": "passed"
            },
            "line": 7,
            "name": "a user is on Motors homepage",
            "match": {
              "location": "co.uk.motors.stepDefinitions.SearchCarsForSaleStepDefinitions.a_user_is_on_Motors_homepage()"
            },
            "keyword": "Given "
          },
          {
            "result": {
              "duration": 187000000,
              "status": "passed"
            },
            "line": 8,
            "name": "user accepts all cookies",
            "match": {
              "location": "co.uk.motors.stepDefinitions.SearchCarsForSaleStepDefinitions.userAcceptsAllCookies()"
            },
            "keyword": "And "
          }
        ]
      },
      {
        "start_timestamp": "2020-04-23T04:32:58.640Z",
        "before": [
          {
            "result": {
              "duration": 5411000000,
              "status": "passed"
            },
            "match": {
              "location": "co.uk.motors.hooks.Hook.setUp()"
            }
          }
        ],
        "line": 19,
        "name": "Customer can read car reviews",
        "description": "",
        "id": "research-cars;customer-can-read-car-reviews;;2",
        "after": [
          {
            "result": {
              "duration": 776000000,
              "status": "passed"
            },
            "match": {
              "location": "co.uk.motors.hooks.Hook.tearDown()"
            }
          }
        ],
        "type": "scenario",
        "keyword": "Scenario Outline",
        "steps": [
          {
            "result": {
              "duration": 124000000,
              "status": "passed"
            },
            "line": 11,
            "name": "user clicks on Reviews",
            "match": {
              "location": "co.uk.motors.stepDefinitions.RegisterToSellACarANDResearchCarsSteps.userClicksOnReviews()"
            },
            "keyword": "And "
          },
          {
            "result": {
              "duration": 215000000,
              "status": "passed"
            },
            "line": 12,
            "name": "user selects \"Buick\" from the vehicle make options",
            "match": {
              "arguments": [
                {
                  "val": "\"Buick\"",
                  "offset": 13
                }
              ],
              "location": "co.uk.motors.stepDefinitions.SearchCarsForSaleStepDefinitions.user_selects_from_the_vehicle_make_options(java.lang.String)"
            },
            "keyword": "And "
          },
          {
            "result": {
              "duration": 159000000,
              "status": "passed"
            },
            "line": 13,
            "name": "user clicks on the View Review button",
            "match": {
              "location": "co.uk.motors.stepDefinitions.RegisterToSellACarANDResearchCarsSteps.userClicksOnTheViewReviewButton()"
            },
            "keyword": "And "
          },
          {
            "result": {
              "duration": 113000000,
              "status": "passed"
            },
            "line": 14,
            "name": "available reviews are displayed for \"Buick\"",
            "match": {
              "arguments": [
                {
                  "val": "\"Buick\"",
                  "offset": 36
                }
              ],
              "location": "co.uk.motors.stepDefinitions.RegisterToSellACarANDResearchCarsSteps.availableReviewsAreDisplayedFor(java.lang.String)"
            },
            "keyword": "Then "
          }
        ]
      }
    ],
    "name": "Research Cars",
    "description": "  As a customer\n  I want to be able to read car reviews\n  So I can have more information",
    "id": "research-cars",
    "keyword": "Feature",
    "uri": "file:src/test/java/co/uk/motors/features/ResearchCars.feature",
    "tags": []
  },
  {
    "line": 2,
    "elements": [
      {
        "line": 7,
        "name": "",
        "description": "",
        "type": "background",
        "keyword": "Background",
        "steps": [
          {
            "result": {
              "duration": 2890000000,
              "status": "passed"
            },
            "line": 8,
            "name": "a user is on Motors homepage",
            "match": {
              "location": "co.uk.motors.stepDefinitions.SearchCarsForSaleStepDefinitions.a_user_is_on_Motors_homepage()"
            },
            "keyword": "Given "
          },
          {
            "result": {
              "duration": 189000000,
              "status": "passed"
            },
            "line": 9,
            "name": "user accepts all cookies",
            "match": {
              "location": "co.uk.motors.stepDefinitions.SearchCarsForSaleStepDefinitions.userAcceptsAllCookies()"
            },
            "keyword": "And "
          }
        ]
      },
      {
        "start_timestamp": "2020-04-23T04:33:08.487Z",
        "before": [
          {
            "result": {
              "duration": 5396000000,
              "status": "passed"
            },
            "match": {
              "location": "co.uk.motors.hooks.Hook.setUp()"
            }
          }
        ],
        "line": 22,
        "name": "Customer can search cars for sale",
        "description": "",
        "id": "search-cars-for-sale;customer-can-search-cars-for-sale;;2",
        "after": [
          {
            "result": {
              "duration": 949000000,
              "status": "passed"
            },
            "match": {
              "location": "co.uk.motors.hooks.Hook.tearDown()"
            }
          }
        ],
        "type": "scenario",
        "keyword": "Scenario Outline",
        "steps": [
          {
            "result": {
              "duration": 317000000,
              "status": "passed"
            },
            "line": 12,
            "name": "user enters \"M400GE\"",
            "match": {
              "arguments": [
                {
                  "val": "\"M400GE\"",
                  "offset": 12
                }
              ],
              "location": "co.uk.motors.stepDefinitions.SearchCarsForSaleStepDefinitions.user_enters(java.lang.String)"
            },
            "keyword": "And "
          },
          {
            "result": {
              "duration": 242000000,
              "status": "passed"
            },
            "line": 13,
            "name": "user selects \"Audi\" from the vehicle make options",
            "match": {
              "arguments": [
                {
                  "val": "\"Audi\"",
                  "offset": 13
                }
              ],
              "location": "co.uk.motors.stepDefinitions.SearchCarsForSaleStepDefinitions.user_selects_from_the_vehicle_make_options(java.lang.String)"
            },
            "keyword": "And "
          },
          {
            "result": {
              "duration": 221000000,
              "status": "passed"
            },
            "line": 14,
            "name": "user selects \"£3,000\" from the minimum price list",
            "match": {
              "arguments": [
                {
                  "val": "\"£3,000\"",
                  "offset": 13
                }
              ],
              "location": "co.uk.motors.stepDefinitions.SearchCarsForSaleStepDefinitions.user_selects_from_the_minimum_price_list(java.lang.String)"
            },
            "keyword": "And "
          },
          {
            "result": {
              "duration": 241000000,
              "status": "passed"
            },
            "line": 15,
            "name": "user selects \"£12,500\" from the maximum price list",
            "match": {
              "arguments": [
                {
                  "val": "\"£12,500\"",
                  "offset": 13
                }
              ],
              "location": "co.uk.motors.stepDefinitions.SearchCarsForSaleStepDefinitions.user_selects_from_the_maximum_price_list(java.lang.String)"
            },
            "keyword": "And "
          },
          {
            "result": {
              "duration": 3298000000,
              "status": "passed"
            },
            "line": 16,
            "name": "user clicks on the search button",
            "match": {
              "location": "co.uk.motors.stepDefinitions.SearchCarsForSaleStepDefinitions.user_clicks_on_the_search_button()"
            },
            "keyword": "And "
          },
          {
            "result": {
              "duration": 94000000,
              "status": "passed"
            },
            "line": 17,
            "name": "a list of vehicle \"Audi\" in \"M400GE\" is displayed",
            "match": {
              "arguments": [
                {
                  "val": "\"Audi\"",
                  "offset": 18
                },
                {
                  "val": "\"M400GE\"",
                  "offset": 28
                }
              ],
              "location": "co.uk.motors.stepDefinitions.SearchCarsForSaleStepDefinitions.a_list_of_vehicle_in_is_displayed(java.lang.String,java.lang.String)"
            },
            "keyword": "Then "
          },
          {
            "result": {
              "duration": 926000000,
              "status": "passed"
            },
            "line": 18,
            "name": "user clicks on one of the result links",
            "match": {
              "location": "co.uk.motors.stepDefinitions.SearchCarsForSaleStepDefinitions.user_clicks_on_one_of_the_result_links()"
            },
            "keyword": "And "
          }
        ],
        "tags": [
          {
            "name": "@regression"
          }
        ]
      }
    ],
    "name": "Search cars for sale",
    "description": "  As a customer\n  I want to be able to search cars for sale\n  So I can get more details about the car",
    "id": "search-cars-for-sale",
    "keyword": "Feature",
    "uri": "file:src/test/java/co/uk/motors/features/SearchCarsForSale.feature",
    "tags": []
  }
]